[
  {
    "ContainingType": "OnlineCourseD2N.Backend.Controllers.CoursesController",
    "Method": "GetCourses",
    "RelativePath": "api/Courses",
    "HttpMethod": "GET",
    "IsController": true,
    "Order": 0,
    "Parameters": [],
    "ReturnTypes": [
      {
        "Type": "System.Collections.Generic.IEnumerable\u00601[[OnlineCourseD2N.Backend.Data.Course, OnlineCourseD2N.Backend, Version=1.0.0.0, Culture=neutral, PublicKeyToken=null]]",
        "MediaTypes": [
          "text/plain",
          "application/json",
          "text/json"
        ],
        "StatusCode": 200
      }
    ]
  },
  {
    "ContainingType": "OnlineCourseD2N.Backend.Controllers.CoursesController",
    "Method": "CreateCourse",
    "RelativePath": "api/Courses",
    "HttpMethod": "POST",
    "IsController": true,
    "Order": 0,
    "Parameters": [
      {
        "Name": "course",
        "Type": "OnlineCourseD2N.Backend.Data.Course",
        "IsRequired": true
      }
    ],
    "ReturnTypes": [
      {
        "Type": "OnlineCourseD2N.Backend.Data.Course",
        "MediaTypes": [
          "text/plain",
          "application/json",
          "text/json"
        ],
        "StatusCode": 200
      }
    ]
  },
  {
    "ContainingType": "OnlineCourseD2N.Backend.Controllers.CoursesController",
    "Method": "GetCourse",
    "RelativePath": "api/Courses/{id}",
    "HttpMethod": "GET",
    "IsController": true,
    "Order": 0,
    "Parameters": [
      {
        "Name": "id",
        "Type": "System.Int32",
        "IsRequired": true
      }
    ],
    "ReturnTypes": [
      {
        "Type": "OnlineCourseD2N.Backend.Data.Course",
        "MediaTypes": [
          "text/plain",
          "application/json",
          "text/json"
        ],
        "StatusCode": 200
      }
    ]
  },
  {
    "ContainingType": "OnlineCourseD2N.Backend.Controllers.CoursesController",
    "Method": "UpdateCourse",
    "RelativePath": "api/Courses/{id}",
    "HttpMethod": "PUT",
    "IsController": true,
    "Order": 0,
    "Parameters": [
      {
        "Name": "id",
        "Type": "System.Int32",
        "IsRequired": true
      },
      {
        "Name": "course",
        "Type": "OnlineCourseD2N.Backend.Data.Course",
        "IsRequired": true
      }
    ],
    "ReturnTypes": []
  },
  {
    "ContainingType": "OnlineCourseD2N.Backend.Controllers.CoursesController",
    "Method": "DeleteCourse",
    "RelativePath": "api/Courses/{id}",
    "HttpMethod": "DELETE",
    "IsController": true,
    "Order": 0,
    "Parameters": [
      {
        "Name": "id",
        "Type": "System.Int32",
        "IsRequired": true
      }
    ],
    "ReturnTypes": []
  },
  {
    "ContainingType": "OnlineCourseD2N.Backend.Controllers.CoursesController",
    "Method": "SearchCourses",
    "RelativePath": "api/Courses/search",
    "HttpMethod": "GET",
    "IsController": true,
    "Order": 0,
    "Parameters": [
      {
        "Name": "keyword",
        "Type": "System.String",
        "IsRequired": false
      }
    ],
    "ReturnTypes": [
      {
        "Type": "System.Collections.Generic.IEnumerable\u00601[[OnlineCourseD2N.Backend.Data.Course, OnlineCourseD2N.Backend, Version=1.0.0.0, Culture=neutral, PublicKeyToken=null]]",
        "MediaTypes": [
          "text/plain",
          "application/json",
          "text/json"
        ],
        "StatusCode": 200
      }
    ]
  },
  {
    "ContainingType": "OnlineCourseD2N.Backend.Controllers.TrainersController",
    "Method": "GetTrainers",
    "RelativePath": "api/Trainers",
    "HttpMethod": "GET",
    "IsController": true,
    "Order": 0,
    "Parameters": [],
    "ReturnTypes": [
      {
        "Type": "System.Collections.Generic.IEnumerable\u00601[[OnlineCourseD2N.Backend.Data.Trainer, OnlineCourseD2N.Backend, Version=1.0.0.0, Culture=neutral, PublicKeyToken=null]]",
        "MediaTypes": [
          "text/plain",
          "application/json",
          "text/json"
        ],
        "StatusCode": 200
      }
    ]
  },
  {
    "ContainingType": "OnlineCourseD2N.Backend.Controllers.TrainersController",
    "Method": "CreateTrainer",
    "RelativePath": "api/Trainers",
    "HttpMethod": "POST",
    "IsController": true,
    "Order": 0,
    "Parameters": [
      {
        "Name": "trainer",
        "Type": "OnlineCourseD2N.Backend.Data.Trainer",
        "IsRequired": true
      }
    ],
    "ReturnTypes": [
      {
        "Type": "OnlineCourseD2N.Backend.Data.Trainer",
        "MediaTypes": [
          "text/plain",
          "application/json",
          "text/json"
        ],
        "StatusCode": 200
      }
    ]
  },
  {
    "ContainingType": "OnlineCourseD2N.Backend.Controllers.TrainersController",
    "Method": "GetTrainer",
    "RelativePath": "api/Trainers/{id}",
    "HttpMethod": "GET",
    "IsController": true,
    "Order": 0,
    "Parameters": [
      {
        "Name": "id",
        "Type": "System.Int32",
        "IsRequired": true
      }
    ],
    "ReturnTypes": [
      {
        "Type": "OnlineCourseD2N.Backend.Data.Trainer",
        "MediaTypes": [
          "text/plain",
          "application/json",
          "text/json"
        ],
        "StatusCode": 200
      }
    ]
  },
  {
    "ContainingType": "OnlineCourseD2N.Backend.Controllers.TrainersController",
    "Method": "UpdateTrainer",
    "RelativePath": "api/Trainers/{id}",
    "HttpMethod": "PUT",
    "IsController": true,
    "Order": 0,
    "Parameters": [
      {
        "Name": "id",
        "Type": "System.Int32",
        "IsRequired": true
      },
      {
        "Name": "trainer",
        "Type": "OnlineCourseD2N.Backend.Data.Trainer",
        "IsRequired": true
      }
    ],
    "ReturnTypes": []
  },
  {
    "ContainingType": "OnlineCourseD2N.Backend.Controllers.TrainersController",
    "Method": "DeleteTrainer",
    "RelativePath": "api/Trainers/{id}",
    "HttpMethod": "DELETE",
    "IsController": true,
    "Order": 0,
    "Parameters": [
      {
        "Name": "id",
        "Type": "System.Int32",
        "IsRequired": true
      }
    ],
    "ReturnTypes": []
  },
  {
    "ContainingType": "OnlineCourseD2N.Backend.Controllers.TrainersController",
    "Method": "SearchTrainers",
    "RelativePath": "api/Trainers/search",
    "HttpMethod": "GET",
    "IsController": true,
    "Order": 0,
    "Parameters": [
      {
        "Name": "keyword",
        "Type": "System.String",
        "IsRequired": false
      }
    ],
    "ReturnTypes": [
      {
        "Type": "System.Collections.Generic.IEnumerable\u00601[[OnlineCourseD2N.Backend.Data.Trainer, OnlineCourseD2N.Backend, Version=1.0.0.0, Culture=neutral, PublicKeyToken=null]]",
        "MediaTypes": [
          "text/plain",
          "application/json",
          "text/json"
        ],
        "StatusCode": 200
      }
    ]
  },
  {
    "ContainingType": "OnlineCourseD2N.Backend.Controllers.UploadsController",
    "Method": "UploadFile",
    "RelativePath": "api/Uploads/UploadFile",
    "HttpMethod": "POST",
    "IsController": true,
    "Order": 0,
    "Parameters": [
      {
        "Name": "file",
        "Type": "Microsoft.AspNetCore.Http.IFormFile",
        "IsRequired": false
      }
    ],
    "ReturnTypes": []
  },
  {
    "ContainingType": "OnlineCourseD2N.Backend.Controllers.WeatherForecastController",
    "Method": "Get",
    "RelativePath": "WeatherForecast",
    "HttpMethod": "GET",
    "IsController": true,
    "Order": 0,
    "Parameters": [],
    "ReturnTypes": [
      {
        "Type": "System.Collections.Generic.IEnumerable\u00601[[OnlineCourseD2N.Backend.WeatherForecast, OnlineCourseD2N.Backend, Version=1.0.0.0, Culture=neutral, PublicKeyToken=null]]",
        "MediaTypes": [
          "text/plain",
          "application/json",
          "text/json"
        ],
        "StatusCode": 200
      }
    ],
    "EndpointName": "GetWeatherForecast"
  }
]